universal_tool_server/__init__.py
universal_tool_server/_version.py
universal_tool_server/mcp.py
universal_tool_server/root.py
universal_tool_server/tools.py
universal_tool_server/auth/__init__.py
universal_tool_server/auth/exceptions.py
universal_tool_server/auth/middleware.py
universal_tool_server/auth/types.py
universal_tool_server-0.0.3.dist-info/METADATA
universal_tool_server-0.0.3.dist-info/WHEEL
universal_tool_server-0.0.3.dist-info/RECORD
