Metadata-Version: 2.4
Name: universal-tool-server
Version: 0.0.3
Summary: Universal Tool Server (Python)
Project-URL: repository, https://github.com/langchain-ai/universal-tool-server
Requires-Python: >=3.10
Requires-Dist: fastapi>=0.110.0
Requires-Dist: jsonschema-rs>=0.20.1
Requires-Dist: langchain-core>=0.2.0
Requires-Dist: mcp>=1.3.0
Requires-Dist: orjson>=3.10.15
Requires-Dist: pydantic>=2.7.2
Requires-Dist: structlog>=20.1.0
